c2pie/__init__.py
c2pie/c2pa/__init__.py
c2pie/c2pa/assertion.py
c2pie/c2pa/assertion_store.py
c2pie/c2pa/claim.py
c2pie/c2pa/claim_signature.py
c2pie/c2pa/config.py
c2pie/c2pa/manifest.py
c2pie/c2pa/manifest_store.py
c2pie/c2pa_injection/__init__.py
c2pie/c2pa_injection/jpg_injection.py
c2pie/c2pa_injection/pdf_injection.py
c2pie/interface.py
c2pie/jumbf_boxes/__init__.py
c2pie/jumbf_boxes/box.py
c2pie/jumbf_boxes/content_box.py
c2pie/jumbf_boxes/description_box.py
c2pie/jumbf_boxes/super_box.py
c2pie/main.py
c2pie/signing.py
c2pie/utils/__init__.py
c2pie/utils/assertion_schemas.py
c2pie/utils/content_types.py
c2pie-0.1.0.dist-info/METADATA
c2pie-0.1.0.dist-info/WHEEL
c2pie-0.1.0.dist-info/entry_points.txt
c2pie-0.1.0.dist-info/licenses/LICENSE
c2pie-0.1.0.dist-info/RECORD
